polygon_caller/PolygonCaller.py
polygon_caller/__init__.py
polygon_caller_hw1_data_eng-0.1.1.dist-info/METADATA
polygon_caller_hw1_data_eng-0.1.1.dist-info/WHEEL
polygon_caller_hw1_data_eng-0.1.1.dist-info/top_level.txt
polygon_caller_hw1_data_eng-0.1.1.dist-info/RECORD
